usb_gadget/__init__.py
usb_gadget/hid_gadget.py
usb_gadget/usb_gadget.py
usb_gadget-0.2.dist-info/LICENSE
usb_gadget-0.2.dist-info/METADATA
usb_gadget-0.2.dist-info/WHEEL
usb_gadget-0.2.dist-info/top_level.txt
usb_gadget-0.2.dist-info/RECORD
