Metadata-Version: 2.1
Name: usb_gadget
Version: 0.2
Summary: A python library for creating and interfacing with USB Gadgets on Linux through libcomposite
Author: Frederic98
Project-URL: Homepage, https://github.com/Frederic98/USBGadget
Project-URL: Bug Tracker, https://github.com/Frederic98/USBGadget/issues
Classifier: Programming Language :: Python :: 3
Classifier: License :: OSI Approved :: MIT License
Classifier: Operating System :: OS Independent
Requires-Python: >=3.7
License-File: LICENSE
